LICENSE
MANIFEST.in
README.rst
setup.py
django_legal.egg-info/PKG-INFO
django_legal.egg-info/SOURCES.txt
django_legal.egg-info/dependency_links.txt
django_legal.egg-info/top_level.txt
legal/__init__.py
legal/exceptions.py
legal/middleware.py
legal/models.py
legal/tests.py
legal/urls.py
legal/views.py
legal/templates/legal/privacy.html
legal/templates/legal/tos.html
legal/templates/legal/tos_accept.html